{
  "_comment": "DO NOT EDIT MANUALLY - See ../../../README.md",
  "fetching_since": "2018-09-12T15:32:16.663Z",
  "name": "Syrun",
  "full_name": "aloisdg/Syrun",
  "owner": "aloisdg",
  "private": false,
  "html_url": "https://github.com/aloisdg/Syrun",
  "description": "Syrun is a stuff selector.",
  "fork": false,
  "url": "https://api.github.com/repos/aloisdg/Syrun",
  "languages_url": "https://api.github.com/repos/aloisdg/Syrun/languages",
  "pulls_url": "https://api.github.com/repos/aloisdg/Syrun/pulls{/number}",
  "created_at": "2015-05-17T21:06:11Z",
  "updated_at": "2015-05-17T21:56:57Z",
  "pushed_at": "2015-06-07T12:14:39Z",
  "homepage": null,
  "size": 168,
  "stargazers_count": 0,
  "language": "C#",
  "mirror_url": null,
  "archived": false,
  "license": {
    "key": "mit",
    "name": "MIT License",
    "spdx_id": "MIT",
    "url": "https://api.github.com/licenses/mit",
    "node_id": "MDc6TGljZW5zZTEz"
  },
  "default_branch": "master"
}
