{
  "_comment": "DO NOT EDIT MANUALLY - See ../../../README.md",
  "fetching_since": "2018-09-12T15:40:59.651Z",
  "name": "tail_log",
  "full_name": "d4be4st/tail_log",
  "owner": "d4be4st",
  "private": false,
  "html_url": "https://github.com/d4be4st/tail_log",
  "description": "Tails your logs",
  "fork": false,
  "url": "https://api.github.com/repos/d4be4st/tail_log",
  "languages_url": "https://api.github.com/repos/d4be4st/tail_log/languages",
  "pulls_url": "https://api.github.com/repos/d4be4st/tail_log/pulls{/number}",
  "created_at": "2013-10-14T13:43:49Z",
  "updated_at": "2013-10-14T14:07:06Z",
  "pushed_at": "2013-10-14T14:07:06Z",
  "homepage": null,
  "size": 112,
  "stargazers_count": 0,
  "language": "Ruby",
  "mirror_url": null,
  "archived": false,
  "license": {
    "key": "mit",
    "name": "MIT License",
    "spdx_id": "MIT",
    "url": "https://api.github.com/licenses/mit",
    "node_id": "MDc6TGljZW5zZTEz"
  },
  "default_branch": "master"
}
