{
  "_comment": "DO NOT EDIT MANUALLY - See ../../../README.md",
  "fetching_since": "2018-09-12T15:49:31.804Z",
  "name": "foursquare",
  "full_name": "wheely/foursquare",
  "owner": "wheely",
  "private": false,
  "html_url": "https://github.com/wheely/foursquare",
  "description": "EM foursquare client",
  "fork": false,
  "url": "https://api.github.com/repos/wheely/foursquare",
  "languages_url": "https://api.github.com/repos/wheely/foursquare/languages",
  "pulls_url": "https://api.github.com/repos/wheely/foursquare/pulls{/number}",
  "created_at": "2011-07-28T13:41:13Z",
  "updated_at": "2017-11-12T12:45:38Z",
  "pushed_at": "2011-12-22T09:26:26Z",
  "homepage": "",
  "size": 94,
  "stargazers_count": 0,
  "language": "Ruby",
  "mirror_url": null,
  "archived": false,
  "license": null,
  "default_branch": "master",
  "organization": {
    "login": "wheely",
    "id": 255694,
    "node_id": "MDEyOk9yZ2FuaXphdGlvbjI1NTY5NA==",
    "avatar_url": "https://avatars3.githubusercontent.com/u/255694?v=4",
    "gravatar_id": "",
    "url": "https://api.github.com/users/wheely",
    "html_url": "https://github.com/wheely",
    "followers_url": "https://api.github.com/users/wheely/followers",
    "following_url": "https://api.github.com/users/wheely/following{/other_user}",
    "gists_url": "https://api.github.com/users/wheely/gists{/gist_id}",
    "starred_url": "https://api.github.com/users/wheely/starred{/owner}{/repo}",
    "subscriptions_url": "https://api.github.com/users/wheely/subscriptions",
    "organizations_url": "https://api.github.com/users/wheely/orgs",
    "repos_url": "https://api.github.com/users/wheely/repos",
    "events_url": "https://api.github.com/users/wheely/events{/privacy}",
    "received_events_url": "https://api.github.com/users/wheely/received_events",
    "type": "Organization",
    "site_admin": false
  }
}
