{
  "_comment": "DO NOT EDIT MANUALLY - See ../../../README.md",
  "fetching_since": "2018-09-12T15:54:39.424Z",
  "name": "noflo-gulp-mocha",
  "full_name": "paulyoung/noflo-gulp-mocha",
  "owner": "paulyoung",
  "private": false,
  "html_url": "https://github.com/paulyoung/noflo-gulp-mocha",
  "description": "gulp-mocha components for NoFlo.",
  "fork": false,
  "url": "https://api.github.com/repos/paulyoung/noflo-gulp-mocha",
  "languages_url": "https://api.github.com/repos/paulyoung/noflo-gulp-mocha/languages",
  "pulls_url": "https://api.github.com/repos/paulyoung/noflo-gulp-mocha/pulls{/number}",
  "created_at": "2014-07-09T04:05:52Z",
  "updated_at": "2014-09-08T20:00:10Z",
  "pushed_at": "2015-02-16T22:34:17Z",
  "homepage": "",
  "size": 200,
  "stargazers_count": 0,
  "language": "CoffeeScript",
  "mirror_url": null,
  "archived": false,
  "license": {
    "key": "mit",
    "name": "MIT License",
    "spdx_id": "MIT",
    "url": "https://api.github.com/licenses/mit",
    "node_id": "MDc6TGljZW5zZTEz"
  },
  "default_branch": "master"
}
