{
  "_comment": "DO NOT EDIT MANUALLY - See ../../../README.md",
  "fetching_since": "2018-09-12T15:46:09.795Z",
  "name": "open-event-server",
  "full_name": "jamesgeorge007/open-event-server",
  "owner": "jamesgeorge007",
  "private": false,
  "html_url": "https://github.com/jamesgeorge007/open-event-server",
  "description": "The Open Event Organizer Server to Manage Events",
  "fork": true,
  "url": "https://api.github.com/repos/jamesgeorge007/open-event-server",
  "languages_url": "https://api.github.com/repos/jamesgeorge007/open-event-server/languages",
  "pulls_url": "https://api.github.com/repos/jamesgeorge007/open-event-server/pulls{/number}",
  "created_at": "2018-05-25T06:23:32Z",
  "updated_at": "2018-07-02T14:27:09Z",
  "pushed_at": "2018-07-02T14:26:55Z",
  "homepage": "http://open-event-api.herokuapp.com/",
  "size": 44797,
  "stargazers_count": 0,
  "language": "Python",
  "mirror_url": null,
  "archived": false,
  "license": {
    "key": "other",
    "name": "Other",
    "spdx_id": null,
    "url": null,
    "node_id": "MDc6TGljZW5zZTA="
  },
  "default_branch": "development"
}
