{
  "_comment": "DO NOT EDIT MANUALLY - See ../../../README.md",
  "name": "firstaidgit",
  "full_name": "magalhini/firstaidgit",
  "owner": "magalhini",
  "private": false,
  "html_url": "https://github.com/magalhini/firstaidgit",
  "description": "First Aid Git",
  "fork": false,
  "url": "https://api.github.com/repos/magalhini/firstaidgit",
  "languages_url": "https://api.github.com/repos/magalhini/firstaidgit/languages",
  "created_at": "2015-03-23T18:04:05Z",
  "updated_at": "2018-07-31T22:41:50Z",
  "pushed_at": "2018-05-29T14:06:07Z",
  "homepage": null,
  "size": 448,
  "stargazers_count": 258,
  "language": "JavaScript",
  "mirror_url": null,
  "archived": false,
  "license": {
    "key": "mit",
    "name": "MIT License",
    "spdx_id": "MIT",
    "url": "https://api.github.com/licenses/mit",
    "node_id": "MDc6TGljZW5zZTEz"
  },
  "default_branch": "master",
  "languages": {
    "JavaScript": {
      "bytes": 22315,
      "color": "#f1e05a"
    },
    "HTML": {
      "bytes": 18422,
      "color": "#e34c26"
    },
    "CSS": {
      "bytes": 12873,
      "color": "#563d7c"
    }
  },
  "contributors": {
    "kostasx": 1,
    "jaapie": 1,
    "davidmaneuver": 1,
    "eliotsykes": 1,
    "yannbertrand": 1,
    "tjl2": 1,
    "atuttle": 1,
    "kcarta": 1,
    "donkirkby": 1,
    "lantrix": 1,
    "kielabokkie": 1,
    "che-effe": 1,
    "Dylan-Buth": 1,
    "Couto": 2,
    "thomastoye": 2,
    "robcalcroft": 2,
    "magalhini": 3,
    "atishgoswami": 3
  },
  "fetched_at": "2018-08-01T10:42:25.848Z"
}
