{
  "_comment": "DO NOT EDIT MANUALLY - See ../../../README.md",
  "fetching_since": "2018-09-12T15:54:52.252Z",
  "name": "poe-map-trade",
  "full_name": "petter-kaspersen/poe-map-trade",
  "owner": "petter-kaspersen",
  "private": false,
  "html_url": "https://github.com/petter-kaspersen/poe-map-trade",
  "description": "A Path of Exile trading website that will show you users that have all of the listed maps you want to buy",
  "fork": false,
  "url": "https://api.github.com/repos/petter-kaspersen/poe-map-trade",
  "languages_url": "https://api.github.com/repos/petter-kaspersen/poe-map-trade/languages",
  "pulls_url": "https://api.github.com/repos/petter-kaspersen/poe-map-trade/pulls{/number}",
  "created_at": "2018-09-08T20:21:57Z",
  "updated_at": "2018-09-08T21:34:23Z",
  "pushed_at": "2018-09-08T21:34:21Z",
  "homepage": null,
  "size": 98,
  "stargazers_count": 0,
  "language": "Elixir",
  "mirror_url": null,
  "archived": false,
  "license": null,
  "default_branch": "master"
}
