{
  "_comment": "DO NOT EDIT MANUALLY - See ../../../README.md",
  "fetching_since": "2018-09-12T15:52:44.823Z",
  "name": "efs-hh",
  "full_name": "ebawam123/efs-hh",
  "owner": "ebawam123",
  "private": false,
  "html_url": "https://github.com/ebawam123/efs-hh",
  "description": "projet application don du sang pour l'établissement  français du sang. Hackathon Hacking-Health Besancon",
  "fork": false,
  "url": "https://api.github.com/repos/ebawam123/efs-hh",
  "languages_url": "https://api.github.com/repos/ebawam123/efs-hh/languages",
  "pulls_url": "https://api.github.com/repos/ebawam123/efs-hh/pulls{/number}",
  "created_at": "2017-10-13T20:52:29Z",
  "updated_at": "2017-10-14T01:08:50Z",
  "pushed_at": "2017-10-14T01:13:17Z",
  "homepage": null,
  "size": 70,
  "stargazers_count": 0,
  "language": "JavaScript",
  "mirror_url": null,
  "archived": false,
  "license": null,
  "default_branch": "master"
}
