{
  "_comment": "DO NOT EDIT MANUALLY - See ../../../README.md",
  "fetching_since": "2018-09-12T15:53:01.297Z",
  "name": "typescript-eip-demo",
  "full_name": "nmt1994/typescript-eip-demo",
  "owner": "nmt1994",
  "private": false,
  "html_url": "https://github.com/nmt1994/typescript-eip-demo",
  "description": "A demonstration of EIP patterns using Typescript and RxJS",
  "fork": false,
  "url": "https://api.github.com/repos/nmt1994/typescript-eip-demo",
  "languages_url": "https://api.github.com/repos/nmt1994/typescript-eip-demo/languages",
  "pulls_url": "https://api.github.com/repos/nmt1994/typescript-eip-demo/pulls{/number}",
  "created_at": "2018-03-10T13:25:49Z",
  "updated_at": "2018-04-12T22:33:27Z",
  "pushed_at": "2018-04-12T22:33:26Z",
  "homepage": null,
  "size": 80,
  "stargazers_count": 0,
  "language": "TypeScript",
  "mirror_url": null,
  "archived": false,
  "license": {
    "key": "mit",
    "name": "MIT License",
    "spdx_id": "MIT",
    "url": "https://api.github.com/licenses/mit",
    "node_id": "MDc6TGljZW5zZTEz"
  },
  "default_branch": "master"
}
