{
  "_comment": "DO NOT EDIT MANUALLY - See ../../../README.md",
  "name": "indevelopment.ca",
  "full_name": "in-development-ca/indevelopment.ca",
  "owner": "in-development-ca",
  "private": false,
  "html_url": "https://github.com/in-development-ca/indevelopment.ca",
  "description": "Our beautiful website",
  "fork": false,
  "url": "https://api.github.com/repos/in-development-ca/indevelopment.ca",
  "languages_url": "https://api.github.com/repos/in-development-ca/indevelopment.ca/languages",
  "created_at": "2017-04-07T20:05:10Z",
  "updated_at": "2018-04-07T16:56:33Z",
  "pushed_at": "2018-04-07T16:56:32Z",
  "homepage": "http://indevelopment.ca",
  "size": 41,
  "stargazers_count": 3,
  "language": "CSS",
  "mirror_url": null,
  "archived": false,
  "license": {
    "key": "mit",
    "name": "MIT License",
    "spdx_id": "MIT",
    "url": "https://api.github.com/licenses/mit",
    "node_id": "MDc6TGljZW5zZTEz"
  },
  "default_branch": "master",
  "organization": {
    "login": "in-development-ca",
    "id": 27027654,
    "node_id": "MDEyOk9yZ2FuaXphdGlvbjI3MDI3NjU0",
    "avatar_url": "https://avatars2.githubusercontent.com/u/27027654?v=4",
    "gravatar_id": "",
    "url": "https://api.github.com/users/in-development-ca",
    "html_url": "https://github.com/in-development-ca",
    "followers_url": "https://api.github.com/users/in-development-ca/followers",
    "following_url": "https://api.github.com/users/in-development-ca/following{/other_user}",
    "gists_url": "https://api.github.com/users/in-development-ca/gists{/gist_id}",
    "starred_url": "https://api.github.com/users/in-development-ca/starred{/owner}{/repo}",
    "subscriptions_url": "https://api.github.com/users/in-development-ca/subscriptions",
    "organizations_url": "https://api.github.com/users/in-development-ca/orgs",
    "repos_url": "https://api.github.com/users/in-development-ca/repos",
    "events_url": "https://api.github.com/users/in-development-ca/events{/privacy}",
    "received_events_url": "https://api.github.com/users/in-development-ca/received_events",
    "type": "Organization",
    "site_admin": false
  },
  "languages": {
    "CSS": {
      "bytes": 16648,
      "color": "#563d7c"
    },
    "HTML": {
      "bytes": 12221,
      "color": "#e34c26"
    },
    "Ruby": {
      "bytes": 3570,
      "color": "#701516"
    },
    "JavaScript": {
      "bytes": 348,
      "color": "#f1e05a"
    }
  },
  "contributors": {
    "juliehache": 1,
    "dxnn": 3,
    "RichardLitt": 6,
    "kvirani": 6
  },
  "fetched_at": "2018-07-20T05:20:21.309Z",
  "pulls_url": "https://api.github.com/repos/in-development-ca/indevelopment.ca/pulls{/number}",
  "pulls_authors": []
}
