{
  "_comment": "DO NOT EDIT MANUALLY - See ../../../README.md",
  "fetching_since": "2018-09-12T15:33:38.035Z",
  "name": "anishkny.github.io",
  "full_name": "anishkny/anishkny.github.io",
  "owner": "anishkny",
  "private": false,
  "html_url": "https://github.com/anishkny/anishkny.github.io",
  "description": null,
  "fork": false,
  "url": "https://api.github.com/repos/anishkny/anishkny.github.io",
  "languages_url": "https://api.github.com/repos/anishkny/anishkny.github.io/languages",
  "pulls_url": "https://api.github.com/repos/anishkny/anishkny.github.io/pulls{/number}",
  "created_at": "2017-04-15T15:52:23Z",
  "updated_at": "2017-04-15T19:01:19Z",
  "pushed_at": "2017-04-15T19:01:17Z",
  "homepage": null,
  "size": 3,
  "stargazers_count": 0,
  "language": "Ruby",
  "mirror_url": null,
  "archived": false,
  "license": null,
  "default_branch": "master"
}
