{
  "_comment": "DO NOT EDIT MANUALLY - See ../../../README.md",
  "fetching_since": "2018-09-12T15:51:15.737Z",
  "name": "Deploy-to-GH-Pages",
  "full_name": "mikelothar/Deploy-to-GH-Pages",
  "owner": "mikelothar",
  "private": false,
  "html_url": "https://github.com/mikelothar/Deploy-to-GH-Pages",
  "description": "A step-by-step guide in 10 easy steps on how to setup auto-deployment to GH-Pages via TravisCI.",
  "fork": false,
  "url": "https://api.github.com/repos/mikelothar/Deploy-to-GH-Pages",
  "languages_url": "https://api.github.com/repos/mikelothar/Deploy-to-GH-Pages/languages",
  "pulls_url": "https://api.github.com/repos/mikelothar/Deploy-to-GH-Pages/pulls{/number}",
  "created_at": "2016-11-19T11:42:27Z",
  "updated_at": "2018-04-08T09:44:09Z",
  "pushed_at": "2018-04-08T09:41:19Z",
  "homepage": "",
  "size": 48,
  "stargazers_count": 0,
  "language": "Shell",
  "mirror_url": null,
  "archived": false,
  "license": null,
  "default_branch": "master"
}
