{
  "_comment": "DO NOT EDIT MANUALLY - See ../../../README.md",
  "fetching_since": "2018-09-12T15:42:01.957Z",
  "name": "imports",
  "full_name": "dufferzafar/imports",
  "owner": "dufferzafar",
  "private": false,
  "html_url": "https://github.com/dufferzafar/imports",
  "description": "Visualize dependencies among python modules using NetworkX and d3.js",
  "fork": false,
  "url": "https://api.github.com/repos/dufferzafar/imports",
  "languages_url": "https://api.github.com/repos/dufferzafar/imports/languages",
  "pulls_url": "https://api.github.com/repos/dufferzafar/imports/pulls{/number}",
  "created_at": "2016-06-11T19:56:45Z",
  "updated_at": "2016-12-19T18:33:34Z",
  "pushed_at": "2016-06-11T20:22:17Z",
  "homepage": "",
  "size": 97,
  "stargazers_count": 0,
  "language": "Python",
  "mirror_url": null,
  "archived": false,
  "license": null,
  "default_branch": "master"
}
