{
  "_comment": "DO NOT EDIT MANUALLY - See ../../../README.md",
  "fetching_since": "2018-09-12T15:50:36.245Z",
  "name": "weekly-achievements-template",
  "full_name": "mdibaiee/weekly-achievements-template",
  "owner": "mdibaiee",
  "private": false,
  "html_url": "https://github.com/mdibaiee/weekly-achievements-template",
  "description": "My weekly achievements",
  "fork": false,
  "url": "https://api.github.com/repos/mdibaiee/weekly-achievements-template",
  "languages_url": "https://api.github.com/repos/mdibaiee/weekly-achievements-template/languages",
  "pulls_url": "https://api.github.com/repos/mdibaiee/weekly-achievements-template/pulls{/number}",
  "created_at": "2015-09-23T21:54:36Z",
  "updated_at": "2015-09-23T21:54:36Z",
  "pushed_at": "2015-09-23T21:55:08Z",
  "homepage": null,
  "size": 84,
  "stargazers_count": 0,
  "language": null,
  "mirror_url": null,
  "archived": false,
  "license": null,
  "default_branch": "master"
}
