{
  "_comment": "DO NOT EDIT MANUALLY - See ../../../README.md",
  "fetching_since": "2018-09-12T15:54:21.698Z",
  "name": "birthday_machine",
  "full_name": "paulhoule/birthday_machine",
  "owner": "paulhoule",
  "private": false,
  "html_url": "https://github.com/paulhoule/birthday_machine",
  "description": null,
  "fork": false,
  "url": "https://api.github.com/repos/paulhoule/birthday_machine",
  "languages_url": "https://api.github.com/repos/paulhoule/birthday_machine/languages",
  "pulls_url": "https://api.github.com/repos/paulhoule/birthday_machine/pulls{/number}",
  "created_at": "2014-03-22T17:47:13Z",
  "updated_at": "2014-06-01T21:07:00Z",
  "pushed_at": "2014-06-01T21:07:00Z",
  "homepage": null,
  "size": 234,
  "stargazers_count": 0,
  "language": "Java",
  "mirror_url": null,
  "archived": false,
  "license": null,
  "default_branch": "master"
}
