{
  "_comment": "DO NOT EDIT MANUALLY - See ../../../README.md",
  "fetching_since": "2018-09-12T15:41:16.768Z",
  "name": "FlappyBird",
  "full_name": "debck/FlappyBird",
  "owner": "debck",
  "private": false,
  "html_url": "https://github.com/debck/FlappyBird",
  "description": "See in action here: https://debck-flappybird.glitch.me/",
  "fork": false,
  "url": "https://api.github.com/repos/debck/FlappyBird",
  "languages_url": "https://api.github.com/repos/debck/FlappyBird/languages",
  "pulls_url": "https://api.github.com/repos/debck/FlappyBird/pulls{/number}",
  "created_at": "2018-05-30T11:27:04Z",
  "updated_at": "2018-06-21T14:44:39Z",
  "pushed_at": "2018-06-18T15:46:11Z",
  "homepage": "",
  "size": 179,
  "stargazers_count": 0,
  "language": "JavaScript",
  "mirror_url": null,
  "archived": false,
  "license": {
    "key": "mit",
    "name": "MIT License",
    "spdx_id": "MIT",
    "url": "https://api.github.com/licenses/mit",
    "node_id": "MDc6TGljZW5zZTEz"
  },
  "default_branch": "master"
}
